phoenix/__init__.py
phoenix/__main__.py
phoenix/build.py
phoenix/minify.py
phoenix/ppm.py
phoenix/serve.py
phoenix_ws-2.1.0.dist-info/METADATA
phoenix_ws-2.1.0.dist-info/UNLICENSE
phoenix_ws-2.1.0.dist-info/WHEEL
phoenix_ws-2.1.0.dist-info/entry_points.txt
phoenix_ws-2.1.0.dist-info/top_level.txt
phoenix_ws-2.1.0.dist-info/RECORD
