Metadata-Version: 2.2
Name: phoenix-ws
Version: 2.1.0
Summary: Speedy alternative web server
Home-page: https://codeberg.org/novaandromeda/phoenix
Author: Nova
Author-email: froggo8311@proton.me
License: UNLICENSE
Keywords: Phoenix,Website,Web,Webserver,Server,Package Manager,HTML,CSS,JavaScript,JS,Fast
Classifier: Programming Language :: Python :: 3
License-File: UNLICENSE
Requires-Dist: flask
Requires-Dist: waitress
Dynamic: author
Dynamic: author-email
Dynamic: classifier
Dynamic: description
Dynamic: description-content-type
Dynamic: home-page
Dynamic: keywords
Dynamic: license
Dynamic: requires-dist
Dynamic: summary
